potatodb/__init__.py
potatodb/db.py
potatodb-1.0.3.dist-info/LICENSE.rst
potatodb-1.0.3.dist-info/METADATA
potatodb-1.0.3.dist-info/WHEEL
potatodb-1.0.3.dist-info/top_level.txt
potatodb-1.0.3.dist-info/RECORD
