Metadata-Version: 2.1
Name: potatodb
Version: 1.0.3
Summary: PotatoDB is a lightweight, file-based NoSQL database for Python projects, designed for easy setup and use in small-scale applications. Ideal for developers seeking simple data persistence without the complexity of traditional databases.
Home-page: https://github.com/Kawai-Senpai/PotatoDB
Download-URL: https://github.com/Kawai-Senpai/PotatoDB
Author: Ranit Bhowmick
Author-email: bhowmickranitking@duck.com
License: MIT License with attribution requirement
Keywords: NoSQL,Database,JSON,Persistence,Lightweight,File-based
License-File: LICENSE.rst
